pythoncom.py
PyWin32.chm
pypiwin32.pth
pypiwin32.version.txt
adodbapi/adodbapi.py
adodbapi/ado_consts.py
adodbapi/is64bit.py
adodbapi/license.txt
adodbapi/readme.txt
adodbapi/schema_table.py
adodbapi/__init__.py
adodbapi/examples/db_print.py
adodbapi/examples/db_table_names.py
adodbapi/examples/xls_read.py
adodbapi/examples/xls_write.py
adodbapi/test/adodbapitest.py
adodbapi/test/adodbapitestconfig.py
adodbapi/test/dbapi20.py
adodbapi/test/is64bit.py
adodbapi/test/setuptestframework.py
adodbapi/test/test_adodbapi_dbapi20.py
adodbapi/test/tryconnection2.py
adodbapi/test/tryconnection3.py
isapi/install.py
isapi/isapicon.py
isapi/PyISAPI_loader.dll
isapi/README.txt
isapi/simple.py
isapi/threaded_extension.py
isapi/__init__.py
isapi/doc/isapi.html
isapi/samples/advanced.py
isapi/samples/README.txt
isapi/samples/redirector.py
isapi/samples/redirector_asynch.py
isapi/samples/redirector_with_filter.py
isapi/samples/test.py
isapi/test/extension_simple.py
isapi/test/README.txt
pythonwin/dde.pyd
pythonwin/license.txt
pythonwin/mfc100u.dll
pythonwin/mfcm100u.dll
pythonwin/Pythonwin.exe
pythonwin/scintilla.dll
pythonwin/win32ui.pyd
pythonwin/win32uiole.pyd
pythonwin/pywin/default.cfg
pythonwin/pywin/IDLE.cfg
pythonwin/pywin/__init__.py
pythonwin/pywin/debugger/configui.py
pythonwin/pywin/debugger/dbgcon.py
pythonwin/pywin/debugger/dbgpyapp.py
pythonwin/pywin/debugger/debugger.py
pythonwin/pywin/debugger/fail.py
pythonwin/pywin/debugger/__init__.py
pythonwin/pywin/Demos/cmdserver.py
pythonwin/pywin/Demos/createwin.py
pythonwin/pywin/Demos/demoutils.py
pythonwin/pywin/Demos/dibdemo.py
pythonwin/pywin/Demos/dlgtest.py
pythonwin/pywin/Demos/dyndlg.py
pythonwin/pywin/Demos/fontdemo.py
pythonwin/pywin/Demos/guidemo.py
pythonwin/pywin/Demos/hiertest.py
pythonwin/pywin/Demos/menutest.py
pythonwin/pywin/Demos/objdoc.py
pythonwin/pywin/Demos/openGLDemo.py
pythonwin/pywin/Demos/progressbar.py
pypiwin32-219.dist-info/DESCRIPTION.rst
pypiwin32-219.dist-info/METADATA
pypiwin32-219.dist-info/metadata.json
pypiwin32-219.dist-info/RECORD
pypiwin32-219.dist-info/WHEEL
